intelmqmail/__init__.py
intelmqmail/cb.py
intelmqmail/db.py
intelmqmail/mail.py
intelmqmail/notification.py
intelmqmail/script.py
intelmqmail/tableformat.py
intelmqmail/templates.py
intelmqmail-1.4.0.dist-info/licenses/COPYING
intelmqmail-1.4.0.dist-info/METADATA
intelmqmail-1.4.0.dist-info/WHEEL
intelmqmail-1.4.0.dist-info/entry_points.txt
intelmqmail-1.4.0.dist-info/top_level.txt
intelmqmail-1.4.0.dist-info/RECORD
