Metadata-Version: 2.4
Name: intelmqmail
Version: 1.4.0
Summary: A mail sending module for IntelMQ
Home-page: https://github.com/intevation/intelmq-mailgen
Author: Intevation GmbH
Author-email: info@intevation.de
Maintainer: Intevation GmbH
Maintainer-email: sebastian.wagner@intevation.de
License: GNU Affero General Public License
Keywords: intelmq mailer postgresql abuse-handling
Classifier: License :: OSI Approved :: GNU Affero General Public License v3 or later (AGPLv3+)
Classifier: License :: OSI Approved :: GNU Lesser General Public License v2 or later (LGPLv2+)
Classifier: Programming Language :: Python :: 3
Classifier: Programming Language :: Python :: 3.6
Classifier: Programming Language :: Python :: 3.7
Classifier: Programming Language :: Python :: 3.8
Classifier: Programming Language :: Python :: 3.9
Classifier: Programming Language :: Python :: 3.10
Classifier: Programming Language :: Python :: 3.11
License-File: COPYING
Requires-Dist: psycopg2
Dynamic: author
Dynamic: author-email
Dynamic: classifier
Dynamic: home-page
Dynamic: keywords
Dynamic: license
Dynamic: license-file
Dynamic: requires-dist
Dynamic: summary
